geeassistant/__init__.py
geeassistant/core.py
geeassistant/graphics.py
geeassistant/indices.py
geeassistant/utils.py
geeassistant-0.1.1.dist-info/licenses/LICENSE
geeassistant-0.1.1.dist-info/METADATA
geeassistant-0.1.1.dist-info/WHEEL
geeassistant-0.1.1.dist-info/top_level.txt
geeassistant-0.1.1.dist-info/RECORD
