Metadata-Version: 2.4
Name: geeassistant
Version: 0.1.1
Summary: A comprehensive Python package to simplify Google Earth Engine learning and usage.
Author-email: Pulakesh Pradhan <pulakesh.mid@gmail.com>
License: MIT
Project-URL: Homepage, https://github.com/pulakeshpradhan/geeassistant
Project-URL: Bug Tracker, https://github.com/pulakeshpradhan/geeassistant/issues
Classifier: Programming Language :: Python :: 3
Classifier: License :: OSI Approved :: MIT License
Classifier: Operating System :: OS Independent
Classifier: Topic :: Scientific/Engineering :: GIS
Requires-Python: >=3.7
License-File: LICENSE
Requires-Dist: earthengine-api>=0.1.300
Requires-Dist: geemap>=0.20.0
Requires-Dist: pandas
Requires-Dist: matplotlib
Requires-Dist: rpy2
Requires-Dist: geopandas
Dynamic: license-file
